{"errors":[],"warnings":[],"namedChunkGroups":{"app":{"chunks":[6,0,3],"assets":["webpack-runtime-328b684a25fd75e25a79.js","webpack-runtime-328b684a25fd75e25a79.js.map","styles.b19e72dc66a68cda8984.css","styles-cf8b16386186695d9cfc.js","styles-cf8b16386186695d9cfc.js.map","app-dd95571193ad2e7044c5.js","app-dd95571193ad2e7044c5.js.map"],"children":{},"childAssets":{}},"component---src-pages-404-js":{"chunks":[0,2,1,4],"assets":["styles.b19e72dc66a68cda8984.css","styles-cf8b16386186695d9cfc.js","styles-cf8b16386186695d9cfc.js.map","2-e6d7eaa143aa2039c8a6.js","2-e6d7eaa143aa2039c8a6.js.map","1-cce5a9d05e2e9820ccbd.js","1-cce5a9d05e2e9820ccbd.js.map","component---src-pages-404-js-885c681ee84e0573302e.js","component---src-pages-404-js-885c681ee84e0573302e.js.map"],"children":{},"childAssets":{}},"component---src-pages-index-js":{"chunks":[0,2,1,5],"assets":["styles.b19e72dc66a68cda8984.css","styles-cf8b16386186695d9cfc.js","styles-cf8b16386186695d9cfc.js.map","2-e6d7eaa143aa2039c8a6.js","2-e6d7eaa143aa2039c8a6.js.map","1-cce5a9d05e2e9820ccbd.js","1-cce5a9d05e2e9820ccbd.js.map","component---src-pages-index-js-1d431bd67999e0eb3750.js","component---src-pages-index-js-1d431bd67999e0eb3750.js.map"],"children":{},"childAssets":{}}},"assetsByChunkName":{"app":["webpack-runtime-328b684a25fd75e25a79.js","styles.b19e72dc66a68cda8984.css","styles-cf8b16386186695d9cfc.js","app-dd95571193ad2e7044c5.js"],"component---src-pages-404-js":["styles.b19e72dc66a68cda8984.css","styles-cf8b16386186695d9cfc.js","2-e6d7eaa143aa2039c8a6.js","1-cce5a9d05e2e9820ccbd.js","component---src-pages-404-js-885c681ee84e0573302e.js"],"component---src-pages-index-js":["styles.b19e72dc66a68cda8984.css","styles-cf8b16386186695d9cfc.js","2-e6d7eaa143aa2039c8a6.js","1-cce5a9d05e2e9820ccbd.js","component---src-pages-index-js-1d431bd67999e0eb3750.js"]}}